{    
    "horticulas": [
        {
            "name": "caviar limão",
            "price": 39,
            "image": "/images/horticulas/caviar-limao.jpg",
            "productId": 10420102025,
            "stock": true
        },
        {
            "name": "nozes",
            "price": 4.5,
            "image": "/images/horticulas/nozes.jpg",
            "productId": 10520102025,
            "stock": true
        },
        {
            "name": "castanhas",
            "price": 4,
            "image": "/images/horticulas/castanhas.jpg",
            "productId": 3615092025,
            "stock": false
        },
        {
            "name": "maracujá",
            "price": 8,
            "image": "/images/frutaDaEpoca/maracuja.jpg",
            "productId": 1618082025,
            "stock": false

        },
        {
            "name": "pêssego paraguaio",
            "price": 3,
            "image": "/images/frutaDaEpoca/pessego-paraguaio.jpg",
            "productId": 234122062025,
            "stock": false

        },
        {
            "name": "ameixa vermelha",
            "price": 3,
            "image": "/images/frutaDaEpoca/ameixa-vermelha.jpg",
            "productId": 2614072025,
            "stock": false
        },
        {
            "name": "marmelos",
            "price": 1.3,
            "image": "/images/frutaDaEpoca/marmelos.jpg",
            "productId": 829092025,
            "stock": true
        },
        {
            "name": "ameixa amarela",
            "price": 3,
            "image": "/images/frutaDaEpoca/ameixa-amarela.jpg",
            "productId": 1121072025,
            "stock": false
        },
        {
            "name": "melancia",
            "price": 2,
            "image": "/images/frutaDaEpoca/melancia.jpg",
            "productId": 2356181124,
            "stock": false

        },
        {
            "name": "figos",
            "price": 6,
            "image": "/images/frutaDaEpoca/figos.jpg",
            "productId": 2357181124,
            "stock": false

        },
        {
            "name": "cucamelon",
            "price": 25,
            "image": "/images/frutaDaEpoca/cucamelon.jpg",
            "productId": 2358181124,
            "stock": true

        },
        {
            "name": "framboesas amarelas",
            "price": 15,
            "image": "/images/frutaDaEpoca/framboesas-amarelas.jpg",
            "productId": 2359181124,
            "stock": false

        },
        {
            "name": "fisalis",
            "price": 15,
            "image": "/images/frutaDaEpoca/fisalis.jpg",
            "productId": 100181124,
            "stock": false

        },
        {
            "name": "mix frutos silvestres",
            "price": 25,
            "image": "/images/frutaDaEpoca/mix-frutos-silvestres.jpg",
            "productId": 12510072025,
            "stock": false

        },
        {
            "name": "morangos",
            "price": 8,
            "image": "/images/frutaDaEpoca/morangos.jpg",
            "productId": 101181124,
            "stock": false

        },
        {
            "name": "morangos silvestres",
            "price": 25,
            "image": "/images/frutaDaEpoca/morangos-silvestres.jpg",
            "productId": 230825052025,
            "stock": false

        },
        {
            "name": "mirtilos",
            "price": 9,
            "image": "/images/frutaDaEpoca/mirtilos.jpg",
            "productId": 11601062025,
            "stock": false
        },
        {
            "name": "amoras",
            "price": 10,
            "image": "/images/frutaDaEpoca/amoras.jpg",
            "productId": 3128072025,
            "stock": false
        },
        {
            "name": "beringela",
            "price": 4,
            "image": "/images/frutaDaEpoca/beringela.jpg",
            "productId": 102181124,
            "stock": true

        },
        {
            "name": "pepino",
            "price": 3,
            "image": "/images/horticulas/pepino.jpg",
            "productId": 103231124,
            "stock": false

        },
        {
            "name": "abóbora manteiga",
            "price": 2,
            "image": "",
            "productId": 51,
            "stock": false

        },
        {
            "name": "abóbora muscade/laranja",
            "price": 2,
            "image": "/images/horticulas/abobora-muscade.jpg",
            "productId": 52,
            "stock": false

        },
        {
            "name": "limões",
            "price": 3,
            "image": "/images/horticulas/limoes.jpg",
            "productId": 53,
            "stock": false

        },
        {
            "name": "tomate chucha",
            "price": 3,
            "image": "/images/horticulas/tomate-chucha.jpg",
            "productId": 3915092025,
            "stock": false
        },
        {
            "name": "tomate coração de boi",
            "price": 4,
            "image": "/images/horticulas/tomate-coracao-boi.jpg",
            "productId": 119,
            "stock": false

        },
        {
            "name": "tomate cherry vermelho",
            "price": 8,
            "image": "/images/horticulas/tomate-cherry-vermelho.jpg",
            "productId": 10707072025,
            "stock": true

        },
        {
            "name": "tomate cherry preto",
            "price": 8,
            "image": "/images/horticulas/tomate-cherry-preto.jpg",
            "productId": 10807072025,
            "stock": true

        },
        {
            "name": "Courgete amarela",
            "price": 4,
            "image": "/images/horticulas/courgete.jpg",
            "productId": 130824032025,
            "stock": false

        },
        {
            "name": "Courgete verde",
            "price": 4,
            "image": "/images/horticulas/courgete-verde.jpg",
            "productId": 204231124,
            "stock": false

        },
        {
            "name": "Courgete baby",
            "price": 10,
            "image": "/images/horticulas/courgete-baby.jpg",
            "productId": 2354181124,
            "stock": false

        },
        {
            "name": "pimentos",
            "price": 4,
            "image": "/images/horticulas/pimentos.jpg",
            "productId": 2352181124,
            "stock": true
        },
        {
            "name": "pimento amarelo",
            "price": 4,
            "image": "/images/horticulas/pimento-amarelo.jpg",
            "productId": 2128072025,
            "stock": true
        },
        {
            "name": "pimento verde",
            "price": 3,
            "image": "/images/horticulas/pimento-verde.jpg",
            "productId": 2355181124,
            "stock": true

        },
        {
            "name": "pimento vermelho",
            "price": 4,
            "image": "",
            "productId": 2728072025,
            "stock": true
        },
        {
            "name": "pimento jalapeno",
            "price": 8,
            "image": "/images/horticulas/pimento-jalapeno.jpg",
            "productId": 10907072025,
            "stock": true
        },
        {
            "name": "pimento albarello",
            "price": 8,
            "image": "/images/horticulas/pimento-albarello.jpg",
            "productId": 2353181124,
            "stock": false
        },
        {
            "name": "pimento padron",
            "price": 10,
            "image": "/images/horticulas/pimento-padron.jpg",
            "productId": 11007072025,
            "stock": false

        },
        {
            "name": "Bagas de goji",
            "price": 25,
            "image": "/images/horticulas/bagas-de-goji.jpg",
            "productId": 120,
            "stock": true

        },
        {
            "name": "chuchu",
            "price": 2.5,
            "image": "/images/horticulas/chuchu.jpg",
            "productId": 123,
            "stock": true

        },
        {
            "name": "tamarilho",
            "price": 9,
            "image": "/images/horticulas/tamarilho.jpg",
            "productId": 124,
            "stock": false

        },
        {
            "name": "laranja",
            "price": 2,
            "image": "/images/frutaDaEpoca/laranja.jpg",
            "productId": 130924032025,
            "stock": false

        }
        
    ]
}
